[
    {
        "data": [
            {
                "allowDdcCi": true,
                "allowSdrSoftwareBrightness": false,
                "autoRotation": "InTabletMode",
                "brightness": 0.2,
                "colorPowerTradeoff": "PreferEfficiency",
                "colorProfileSource": "sRGB",
                "connectorName": "LVDS-1",
                "detectedDdcCi": false,
                "edidHash": "11a28d7d5036ab20e6e5ff3348224e19",
                "edidIdentifier": "LGD 395 0 0 2009 0",
                "edrPolicy": "never",
                "highDynamicRange": false,
                "iccProfilePath": "",
                "maxBitsPerColor": 0,
                "mode": {
                    "height": 768,
                    "refreshRate": 59973,
                    "width": 1366
                },
                "overscan": 0,
                "rgbRange": "Automatic",
                "scale": 1,
                "sdrBrightness": 200,
                "sdrGamutWideness": 0,
                "transform": "Normal",
                "uuid": "5685ddc2-1aef-4a68-832f-0ff17c7bc2fe",
                "vrrPolicy": "Never",
                "wideColorGamut": false
            }
        ],
        "name": "outputs"
    },
    {
        "data": [
            {
                "lidClosed": false,
                "outputs": [
                    {
                        "enabled": true,
                        "outputIndex": 0,
                        "position": {
                            "x": 0,
                            "y": 0
                        },
                        "priority": 0,
                        "replicationSource": ""
                    }
                ]
            },
            {
                "lidClosed": true,
                "outputs": [
                    {
                        "enabled": true,
                        "outputIndex": 0,
                        "position": {
                            "x": 0,
                            "y": 0
                        },
                        "priority": 0,
                        "replicationSource": ""
                    }
                ]
            }
        ],
        "name": "setups"
    }
]
